magnos/__init__.py
magnos/build.py
magnos/common.py
magnos/coupling_test.py
magnos/input.py
magnos/interactions.py
magnos/lattice.py
magnos/linalg.py
magnos/magnons.py
magnos/symmetry.py
magnos/utils.py
magnos-1.0.0.dist-info/licenses/LICENSE
magnos-1.0.0.dist-info/METADATA
magnos-1.0.0.dist-info/WHEEL
magnos-1.0.0.dist-info/top_level.txt
magnos-1.0.0.dist-info/RECORD
