Metadata-Version: 2.4
Name: magnos
Version: 1.0.0
Summary: Magnos is a general, scalable Python code to simulate magnon bandstructures from spin structures and exchange coupling constants.
Author-email: Alex Moorhouse <aem228@cam.ac.uk>, Joseph Barker <j.barker@leeds.ac.uk>, Michele Simoncelli <michele.simoncelli@columbia.edu>
Requires-Python: >=3.12
License-File: LICENSE
Requires-Dist: numpy>=2.0
Requires-Dist: matplotlib>=3.9.2
Requires-Dist: spglib>=2.5
Requires-Dist: ase>=3.23
Requires-Dist: pytest>=7
Dynamic: license-file
